GraFT_Python/__init__.py
GraFT_Python/explainations.py
GraFT_Python/main_functions_graft.py
GraFT_Python/run_graft.py
GraFT_Python/untitled2.py
GraFT_Python-0.0.2.dist-info/LICENSE.txt
GraFT_Python-0.0.2.dist-info/METADATA
GraFT_Python-0.0.2.dist-info/WHEEL
GraFT_Python-0.0.2.dist-info/top_level.txt
GraFT_Python-0.0.2.dist-info/RECORD
